livecheck/__init__.py
livecheck/__main__.py
livecheck/constants.py
livecheck/main.py
livecheck/py.typed
livecheck/settings.py
livecheck/special/__init__.py
livecheck/special/dotnet.py
livecheck/special/golang.py
livecheck/special/handlers.py
livecheck/special/utils.py
livecheck/special/yarn.py
livecheck/typing.py
livecheck/utils/__init__.py
livecheck/utils/portage.py
portage_livecheck-0.0.13.dist-info/LICENSE.txt
portage_livecheck-0.0.13.dist-info/METADATA
portage_livecheck-0.0.13.dist-info/WHEEL
portage_livecheck-0.0.13.dist-info/entry_points.txt
portage_livecheck-0.0.13.dist-info/RECORD
