Metadata-Version: 2.1
Name: portage-livecheck
Version: 0.0.13
Summary: Tool to update ebuilds.
Home-page: https://github.com/Tatsh/livecheck
License: MIT
Keywords: command line,ebuild,gentoo,portage
Author: Andrew Udvare
Author-email: audvare@gmail.com
Requires-Python: >=3.11,<4
Classifier: Development Status :: 4 - Beta
Classifier: Intended Audience :: Developers
Classifier: License :: OSI Approved :: MIT License
Classifier: Programming Language :: Python
Classifier: Programming Language :: Python :: 3
Classifier: Programming Language :: Python :: 3.11
Classifier: Programming Language :: Python :: 3.12
Classifier: Typing :: Typed
Requires-Dist: click (>=8.1.7)
Requires-Dist: loguru (>=0.7.2,<0.8.0)
Requires-Dist: pyxdg (>=0.28,<0.29)
Requires-Dist: pyyaml (>=6.0.1,<7.0.0)
Requires-Dist: requests (>=2.31.0,<3.0.0)
Project-URL: Documentation, https://livecheck.readthedocs.io/
Project-URL: Repository, https://github.com/Tatsh/livecheck
